Metadata-Version: 2.1
Name: bettermdptools
Version: 0.8.1
Summary: so much room for activities
Home-page: https://github.com/jlm429/bettermdptools
Author: John Mansfield
Author-email: jlm429@gmail.com
License: New BSD
Platform: Any
